[
  {
    "id": "iot-f1-1",
    "label": "Lobby Temp",
    "type": "temperature",
    "floorId": "f1",
    "floorName": "Ground Floor",
    "zoneId": "z1",
    "zoneName": "Lobby",
    "x": 45.95,
    "y": 59.24,
    "addedBy": "system",
    "addedAt": "2026-04-19T00:00:00Z"
  },
  {
    "id": "iot-f1-2",
    "label": "Lobby RH",
    "type": "humidity",
    "floorId": "f1",
    "floorName": "Ground Floor",
    "zoneId": "z1",
    "zoneName": "Lobby",
    "x": 55.49,
    "y": 92.67,
    "addedBy": "system",
    "addedAt": "2026-04-19T00:00:00Z"
  },
  {
    "id": "iot-f1-3",
    "label": "Lobby PIR",
    "type": "motion",
    "floorId": "f1",
    "floorName": "Ground Floor",
    "zoneId": "z1",
    "zoneName": "Lobby",
    "x": 2.16,
    "y": 75.74,
    "addedBy": "system",
    "addedAt": "2026-04-19T00:00:00Z"
  },
  {
    "id": "iot-f1-4",
    "label": "Lobby Camera 1",
    "type": "camera",
    "floorId": "f1",
    "floorName": "Ground Floor",
    "zoneId": "z1",
    "zoneName": "Lobby",
    "x": 37.19,
    "y": 79.41,
    "addedBy": "system",
    "addedAt": "2026-04-19T00:00:00Z"
  },
  {
    "id": "iot-f1-5",
    "label": "Server Rack Temp",
    "type": "temperature",
    "floorId": "f1",
    "floorName": "Ground Floor",
    "zoneId": "z2",
    "zoneName": "Server Room",
    "x": 22.53,
    "y": 59.66,
    "addedBy": "system",
    "addedAt": "2026-04-19T00:00:00Z"
  },
  {
    "id": "iot-f1-6",
    "label": "Server Room RH",
    "type": "humidity",
    "floorId": "f1",
    "floorName": "Ground Floor",
    "zoneId": "z2",
    "zoneName": "Server Room",
    "x": 30.89,
    "y": 79.27,
    "addedBy": "system",
    "addedAt": "2026-04-19T00:00:00Z"
  },
  {
    "id": "iot-f1-7",
    "label": "Server Smoke Det.",
    "type": "smoke",
    "floorId": "f1",
    "floorName": "Ground Floor",
    "zoneId": "z2",
    "zoneName": "Server Room",
    "x": 55.98,
    "y": 79.83,
    "addedBy": "system",
    "addedAt": "2026-04-19T00:00:00Z"
  },
  {
    "id": "iot-f1-8",
    "label": "UPS Load",
    "type": "power",
    "floorId": "f1",
    "floorName": "Ground Floor",
    "zoneId": "z2",
    "zoneName": "Server Room",
    "x": 55.1,
    "y": 60.08,
    "addedBy": "system",
    "addedAt": "2026-04-19T00:00:00Z"
  },
  {
    "id": "iot-f2-9",
    "label": "Office-A Temp",
    "type": "temperature",
    "floorId": "f2",
    "floorName": "1st Floor",
    "zoneId": "z3",
    "zoneName": "Open Office A",
    "x": 21.64,
    "y": 21.72,
    "addedBy": "system",
    "addedAt": "2026-04-19T00:00:00Z"
  },
  {
    "id": "iot-f2-10",
    "label": "Office-A CO2",
    "type": "co2",
    "floorId": "f2",
    "floorName": "1st Floor",
    "zoneId": "z3",
    "zoneName": "Open Office A",
    "x": 35,
    "y": 45,
    "addedBy": "system",
    "addedAt": "2026-04-19T00:00:00Z"
  },
  {
    "id": "iot-f2-11",
    "label": "Office-A PIR",
    "type": "motion",
    "floorId": "f2",
    "floorName": "1st Floor",
    "zoneId": "z3",
    "zoneName": "Open Office A",
    "x": 32,
    "y": 50,
    "addedBy": "system",
    "addedAt": "2026-04-19T00:00:00Z"
  },
  {
    "id": "iot-f2-12",
    "label": "Office-A Lux",
    "type": "light",
    "floorId": "f2",
    "floorName": "1st Floor",
    "zoneId": "z3",
    "zoneName": "Open Office A",
    "x": 46.24,
    "y": 88.86,
    "addedBy": "system",
    "addedAt": "2026-04-19T00:00:00Z"
  },
  {
    "id": "iot-f2-13",
    "label": "Meeting-1 Temp",
    "type": "temperature",
    "floorId": "f2",
    "floorName": "1st Floor",
    "zoneId": "z4",
    "zoneName": "Meeting Room 1",
    "x": 60,
    "y": 55,
    "addedBy": "system",
    "addedAt": "2026-04-19T00:00:00Z"
  },
  {
    "id": "iot-f2-14",
    "label": "Meeting-1 CO2",
    "type": "co2",
    "floorId": "f2",
    "floorName": "1st Floor",
    "zoneId": "z4",
    "zoneName": "Meeting Room 1",
    "x": 64,
    "y": 58,
    "addedBy": "system",
    "addedAt": "2026-04-19T00:00:00Z"
  },
  {
    "id": "iot-f2-15",
    "label": "Meeting-1 Door",
    "type": "door",
    "floorId": "f2",
    "floorName": "1st Floor",
    "zoneId": "z4",
    "zoneName": "Meeting Room 1",
    "x": 58,
    "y": 50,
    "addedBy": "system",
    "addedAt": "2026-04-19T00:00:00Z"
  }
]