[
  {
    "id": "iot-f1-1",
    "label": "Server Smoke Det.",
    "type": "smoke",
    "category": "mission_critical",
    "heartbeatSec": 3,
    "floorId": "f1",
    "floorName": "Ground Floor",
    "zoneId": "z2",
    "zoneName": "Server Room",
    "x": 31.19,
    "y": 78.14,
    "addedBy": "system",
    "addedAt": "2026-04-19T00:00:00Z"
  },
  {
    "id": "iot-f1-2",
    "label": "Server Room Door",
    "type": "door",
    "category": "mission_critical",
    "heartbeatSec": 5,
    "floorId": "f1",
    "floorName": "Ground Floor",
    "zoneId": "z2",
    "zoneName": "Server Room",
    "x": 13.18,
    "y": 77.72,
    "addedBy": "system",
    "addedAt": "2026-04-19T00:00:00Z"
  },
  {
    "id": "iot-f1-3",
    "label": "Lobby PIR",
    "type": "motion",
    "category": "mission_critical",
    "heartbeatSec": 5,
    "floorId": "f1",
    "floorName": "Ground Floor",
    "zoneId": "z1",
    "zoneName": "Lobby",
    "x": 55.59,
    "y": 60.79,
    "addedBy": "system",
    "addedAt": "2026-04-19T00:00:00Z"
  },
  {
    "id": "iot-f1-4",
    "label": "Lobby Fire Alarm",
    "type": "fire_alarm",
    "category": "mission_critical",
    "heartbeatSec": 2,
    "floorId": "f1",
    "floorName": "Ground Floor",
    "zoneId": "z1",
    "zoneName": "Lobby",
    "x": 55.69,
    "y": 77.57,
    "addedBy": "system",
    "addedAt": "2026-04-19T00:00:00Z"
  },
  {
    "id": "iot-f1-5",
    "label": "Basement Flood Det.",
    "type": "flood",
    "category": "mission_critical",
    "heartbeatSec": 5,
    "floorId": "f1",
    "floorName": "Ground Floor",
    "zoneId": null,
    "zoneName": null,
    "x": 55.49,
    "y": 92.52,
    "addedBy": "system",
    "addedAt": "2026-04-19T00:00:00Z"
  },
  {
    "id": "iot-f1-6",
    "label": "Lobby Temp",
    "type": "temperature",
    "category": "metering",
    "heartbeatSec": 30,
    "floorId": "f1",
    "floorName": "Ground Floor",
    "zoneId": "z1",
    "zoneName": "Lobby",
    "x": 47.13,
    "y": 60.23,
    "addedBy": "system",
    "addedAt": "2026-04-19T00:00:00Z"
  },
  {
    "id": "iot-f1-7",
    "label": "Lobby RH",
    "type": "humidity",
    "category": "metering",
    "heartbeatSec": 30,
    "floorId": "f1",
    "floorName": "Ground Floor",
    "zoneId": "z1",
    "zoneName": "Lobby",
    "x": 38.17,
    "y": 91.4,
    "addedBy": "system",
    "addedAt": "2026-04-19T00:00:00Z"
  },
  {
    "id": "iot-f1-8",
    "label": "Lobby Camera 1",
    "type": "camera",
    "category": "metering",
    "heartbeatSec": 60,
    "floorId": "f1",
    "floorName": "Ground Floor",
    "zoneId": "z1",
    "zoneName": "Lobby",
    "x": 38.96,
    "y": 60.65,
    "addedBy": "system",
    "addedAt": "2026-04-19T00:00:00Z"
  },
  {
    "id": "iot-f1-9",
    "label": "Server Rack Temp",
    "type": "temperature",
    "category": "metering",
    "heartbeatSec": 15,
    "floorId": "f1",
    "floorName": "Ground Floor",
    "zoneId": "z2",
    "zoneName": "Server Room",
    "x": 21.74,
    "y": 59.94,
    "addedBy": "system",
    "addedAt": "2026-04-19T00:00:00Z"
  },
  {
    "id": "iot-f1-10",
    "label": "Server Room RH",
    "type": "humidity",
    "category": "metering",
    "heartbeatSec": 30,
    "floorId": "f1",
    "floorName": "Ground Floor",
    "zoneId": "z2",
    "zoneName": "Server Room",
    "x": 13.28,
    "y": 91.4,
    "addedBy": "system",
    "addedAt": "2026-04-19T00:00:00Z"
  },
  {
    "id": "iot-f1-11",
    "label": "UPS Load",
    "type": "power",
    "category": "metering",
    "heartbeatSec": 15,
    "floorId": "f1",
    "floorName": "Ground Floor",
    "zoneId": "z2",
    "zoneName": "Server Room",
    "x": 30.7,
    "y": 60.23,
    "addedBy": "system",
    "addedAt": "2026-04-19T00:00:00Z"
  },
  {
    "id": "iot-f1-12",
    "label": "UPS Battery",
    "type": "ups_battery",
    "category": "metering",
    "heartbeatSec": 30,
    "floorId": "f1",
    "floorName": "Ground Floor",
    "zoneId": "z2",
    "zoneName": "Server Room",
    "x": 2.16,
    "y": 90.97,
    "addedBy": "system",
    "addedAt": "2026-04-19T00:00:00Z"
  },
  {
    "id": "iot-f2-13",
    "label": "Meeting-1 Door",
    "type": "door",
    "category": "mission_critical",
    "heartbeatSec": 5,
    "floorId": "f2",
    "floorName": "1st Floor",
    "zoneId": "z4",
    "zoneName": "Meeting Room 1",
    "x": 55.69,
    "y": 23.41,
    "addedBy": "system",
    "addedAt": "2026-04-19T00:00:00Z"
  },
  {
    "id": "iot-f2-14",
    "label": "Office-A Smoke",
    "type": "smoke",
    "category": "mission_critical",
    "heartbeatSec": 3,
    "floorId": "f2",
    "floorName": "1st Floor",
    "zoneId": "z3",
    "zoneName": "Open Office A",
    "x": 30.89,
    "y": 36.95,
    "addedBy": "system",
    "addedAt": "2026-04-19T00:00:00Z"
  },
  {
    "id": "iot-f2-15",
    "label": "Escalator F2 Sensor",
    "type": "escalator",
    "category": "mission_critical",
    "heartbeatSec": 5,
    "floorId": "f2",
    "floorName": "1st Floor",
    "zoneId": null,
    "zoneName": null,
    "x": 55.49,
    "y": 51.9,
    "addedBy": "system",
    "addedAt": "2026-04-19T00:00:00Z"
  },
  {
    "id": "iot-f2-16",
    "label": "AHU-2 Fault",
    "type": "machine_fault",
    "category": "mission_critical",
    "heartbeatSec": 5,
    "floorId": "f2",
    "floorName": "1st Floor",
    "zoneId": null,
    "zoneName": null,
    "x": 6.2,
    "y": 51.34,
    "addedBy": "system",
    "addedAt": "2026-04-19T00:00:00Z"
  },
  {
    "id": "iot-f2-17",
    "label": "Office-A Temp",
    "type": "temperature",
    "category": "metering",
    "heartbeatSec": 30,
    "floorId": "f2",
    "floorName": "1st Floor",
    "zoneId": "z3",
    "zoneName": "Open Office A",
    "x": 20.37,
    "y": 23.41,
    "addedBy": "system",
    "addedAt": "2026-04-19T00:00:00Z"
  },
  {
    "id": "iot-f2-18",
    "label": "Office-A CO2",
    "type": "co2",
    "category": "metering",
    "heartbeatSec": 30,
    "floorId": "f2",
    "floorName": "1st Floor",
    "zoneId": "z3",
    "zoneName": "Open Office A",
    "x": 30.01,
    "y": 23.41,
    "addedBy": "system",
    "addedAt": "2026-04-19T00:00:00Z"
  },
  {
    "id": "iot-f2-19",
    "label": "Office-A Lux",
    "type": "light",
    "category": "metering",
    "heartbeatSec": 60,
    "floorId": "f2",
    "floorName": "1st Floor",
    "zoneId": "z3",
    "zoneName": "Open Office A",
    "x": 13.28,
    "y": 36.11,
    "addedBy": "system",
    "addedAt": "2026-04-19T00:00:00Z"
  },
  {
    "id": "iot-f2-20",
    "label": "Meeting-1 Temp",
    "type": "temperature",
    "category": "metering",
    "heartbeatSec": 30,
    "floorId": "f2",
    "floorName": "1st Floor",
    "zoneId": "z4",
    "zoneName": "Meeting Room 1",
    "x": 46.04,
    "y": 23.13,
    "addedBy": "system",
    "addedAt": "2026-04-19T00:00:00Z"
  },
  {
    "id": "iot-f2-21",
    "label": "Meeting-1 CO2",
    "type": "co2",
    "category": "metering",
    "heartbeatSec": 30,
    "floorId": "f2",
    "floorName": "1st Floor",
    "zoneId": "z4",
    "zoneName": "Meeting Room 1",
    "x": 37.58,
    "y": 37.52,
    "addedBy": "system",
    "addedAt": "2026-04-19T00:00:00Z"
  },
  {
    "id": "iot-f2-22",
    "label": "Meeting-1 Occupancy",
    "type": "occupancy",
    "category": "metering",
    "heartbeatSec": 30,
    "floorId": "f2",
    "floorName": "1st Floor",
    "zoneId": "z4",
    "zoneName": "Meeting Room 1",
    "x": 55.19,
    "y": 38.22,
    "addedBy": "system",
    "addedAt": "2026-04-19T00:00:00Z"
  },
  {
    "id": "iot-f2-23",
    "label": "Office-A PIR",
    "type": "motion",
    "category": "mission_critical",
    "heartbeatSec": 5,
    "floorId": "f2",
    "floorName": "1st Floor",
    "zoneId": "z3",
    "zoneName": "Open Office A",
    "x": 30.79,
    "y": 51.34,
    "addedBy": "system",
    "addedAt": "2026-04-19T00:00:00Z"
  }
]